./.gitignore
./PKG-INFO
./cli.py
./pyproject.toml
./setup.py
./.vscode/settings.json
ahqstore_cli-0.12.1.dist-info/METADATA
ahqstore_cli-0.12.1.dist-info/WHEEL
ahqstore_cli-0.12.1.dist-info/entry_points.txt
ahqstore_cli-0.12.1.dist-info/RECORD
