Metadata-Version: 2.4
Name: ahqstore-cli
Version: 0.12.1
Summary: A modern Python wrapper for the ahqstore CLI
Author-email: AHQ Softwares <ahqsecret@gmail.com>
Classifier: License :: OSI Approved :: MIT License
Classifier: Operating System :: OS Independent
Classifier: Programming Language :: Python :: 3
Requires-Python: >=3.8
Requires-Dist: cffi>=1.17.0
Requires-Dist: requests>=2.25.1
